<?xml version="1.0" ?>
<annotation>
  <folder>images</folder>
  <filename>14_3_scratches_85</filename>
  <path>./data/train_aug/14_3_scratches_85.jpg</path>
  <source>
    <database>Unknown</database>
  </source>
  <size>
    <width>200</width>
    <height>200</height>
    <depth>3</depth>
  </size>
  <segmented>0</segmented>
  <object>
    <name>scratches</name>
    <pose>Unspecified</pose>
    <truncated>0</truncated>
    <difficult>0</difficult>
    <confidence>1.0</confidence>
    <bndbox>
      <xmin>81</xmin>
      <ymin>2</ymin>
      <xmax>97</xmax>
      <ymax>185</ymax>
    </bndbox>
  </object>
  <object>
    <name>scratches</name>
    <pose>Unspecified</pose>
    <truncated>0</truncated>
    <difficult>0</difficult>
    <confidence>1.0</confidence>
    <bndbox>
      <xmin>19</xmin>
      <ymin>1</ymin>
      <xmax>28</xmax>
      <ymax>167</ymax>
    </bndbox>
  </object>
</annotation>
