<?xml version="1.0" ?>
<annotation>
  <folder>images</folder>
  <filename>172_1_inclusion_61</filename>
  <path>./data/train_aug/172_1_inclusion_61.jpg</path>
  <source>
    <database>Unknown</database>
  </source>
  <size>
    <width>200</width>
    <height>200</height>
    <depth>3</depth>
  </size>
  <segmented>0</segmented>
  <object>
    <name>inclusion</name>
    <pose>Unspecified</pose>
    <truncated>0</truncated>
    <difficult>0</difficult>
    <confidence>1.0</confidence>
    <bndbox>
      <xmin>107</xmin>
      <ymin>41</ymin>
      <xmax>141</xmax>
      <ymax>200</ymax>
    </bndbox>
  </object>
  <object>
    <name>inclusion</name>
    <pose>Unspecified</pose>
    <truncated>0</truncated>
    <difficult>0</difficult>
    <confidence>1.0</confidence>
    <bndbox>
      <xmin>81</xmin>
      <ymin>1</ymin>
      <xmax>117</xmax>
      <ymax>164</ymax>
    </bndbox>
  </object>
</annotation>
