<?xml version="1.0" ?>
<annotation>
  <folder>images</folder>
  <filename>385_3_inclusion_34</filename>
  <path>./data/train_aug/385_3_inclusion_34.jpg</path>
  <source>
    <database>Unknown</database>
  </source>
  <size>
    <width>200</width>
    <height>200</height>
    <depth>3</depth>
  </size>
  <segmented>0</segmented>
  <object>
    <name>inclusion</name>
    <pose>Unspecified</pose>
    <truncated>0</truncated>
    <difficult>0</difficult>
    <confidence>1.0</confidence>
    <bndbox>
      <xmin>33</xmin>
      <ymin>17</ymin>
      <xmax>71</xmax>
      <ymax>128</ymax>
    </bndbox>
  </object>
  <object>
    <name>inclusion</name>
    <pose>Unspecified</pose>
    <truncated>0</truncated>
    <difficult>0</difficult>
    <confidence>1.0</confidence>
    <bndbox>
      <xmin>145</xmin>
      <ymin>28</ymin>
      <xmax>180</xmax>
      <ymax>159</ymax>
    </bndbox>
  </object>
  <object>
    <name>inclusion</name>
    <pose>Unspecified</pose>
    <truncated>0</truncated>
    <difficult>0</difficult>
    <confidence>1.0</confidence>
    <bndbox>
      <xmin>102</xmin>
      <ymin>36</ymin>
      <xmax>131</xmax>
      <ymax>96</ymax>
    </bndbox>
  </object>
  <object>
    <name>inclusion</name>
    <pose>Unspecified</pose>
    <truncated>0</truncated>
    <difficult>0</difficult>
    <confidence>1.0</confidence>
    <bndbox>
      <xmin>90</xmin>
      <ymin>140</ymin>
      <xmax>111</xmax>
      <ymax>190</ymax>
    </bndbox>
  </object>
</annotation>
